sampleapp/__init__.py
sampleapp/app.py
sampleapp-0.0.1.dist-info/DESCRIPTION.rst
sampleapp-0.0.1.dist-info/METADATA
sampleapp-0.0.1.dist-info/RECORD
sampleapp-0.0.1.dist-info/WHEEL
sampleapp-0.0.1.dist-info/entry_points.txt
sampleapp-0.0.1.dist-info/metadata.json
sampleapp-0.0.1.dist-info/top_level.txt
sampleapp-0.0.1.dist-info/zip-safe
