Metadata-Version: 2.0
Name: sampleapp
Version: 0.0.1
Summary: a sample project
Home-page: https://github.com/hyteer/pypi-sample
Author: hyteer@gmail.com
Author-email: hyteer@gmail.com
License: MIT
Keywords: python package demo sample
Platform: UNKNOWN
